{"name":"桌沿","slug":"blog-author","avatar":"https://imgs.zhubai.love/c6dfb4dd470244c5bb0835469b9d9781.png","link":"/","description":"这是一段简短的描述","socials":{"github":"https://github.com/TriDiamond","twitter":"","stackoverflow":"","wechat":"","qq":"","weibo":"","zhihu":"","csdn":"","juejin":"","customs":{"sspai":{"icon":"/svg/sspai.svg","link":"https://sspai.com/u/379wzx2e/posts"},"newsletter":{"icon":"/svg/newsletter.svg","link":"https://deskside.zhubai.love"}}},"post_list":[{"title":"Hello World","uid":"b9663f58f18133b35bfe243f3e916a80","slug":"hello-world - 副本 (2)","date":"2022-06-28T04:39:40.096Z","updated":"2022-06-28T04:39:13.210Z","comments":true,"path":"api/articles/hello-world - 副本 (2).json","keywords":null,"cover":null,"text":"Welcome to Hexo! This is your very first post. Check documentation for more info. If you get any problems when using Hexo, you can find the ...","link":"","photos":[],"count_time":{"symbolsCount":440,"symbolsTime":"1 mins."},"categories":[],"tags":[],"author":{"name":"桌沿","slug":"blog-author","avatar":"https://imgs.zhubai.love/c6dfb4dd470244c5bb0835469b9d9781.png","link":"/","description":"这是一段简短的描述","socials":{"github":"https://github.com/TriDiamond","twitter":"","stackoverflow":"","wechat":"","qq":"","weibo":"","zhihu":"","csdn":"","juejin":"","customs":{"sspai":{"icon":"/svg/sspai.svg","link":"https://sspai.com/u/379wzx2e/posts"},"newsletter":{"icon":"/svg/newsletter.svg","link":"https://deskside.zhubai.love"}}}},"feature":true},{"title":"Hello World","uid":"b9663f58f18133b35bfe243f3e916a80","slug":"hello-world","date":"2022-06-28T04:27:02.653Z","updated":"2022-06-28T04:39:13.210Z","comments":true,"path":"api/articles/hello-world.json","keywords":null,"cover":null,"text":"Welcome to Hexo! This is your very first post. Check documentation for more info. If you get any problems when using Hexo, you can find the ...","link":"","photos":[],"count_time":{"symbolsCount":440,"symbolsTime":"1 mins."},"categories":[],"tags":[],"author":{"name":"桌沿","slug":"blog-author","avatar":"https://imgs.zhubai.love/c6dfb4dd470244c5bb0835469b9d9781.png","link":"/","description":"这是一段简短的描述","socials":{"github":"https://github.com/TriDiamond","twitter":"","stackoverflow":"","wechat":"","qq":"","weibo":"","zhihu":"","csdn":"","juejin":"","customs":{"sspai":{"icon":"/svg/sspai.svg","link":"https://sspai.com/u/379wzx2e/posts"},"newsletter":{"icon":"/svg/newsletter.svg","link":"https://deskside.zhubai.love"}}}},"feature":true},{"title":"Article Title","uid":"a6b82868af4785482b869dc5d958966b","slug":"hello-world - 副本","date":"2020-08-15T10:49:36.000Z","updated":"2022-06-28T07:09:28.403Z","comments":true,"path":"api/articles/hello-world - 副本.json","keywords":null,"cover":"https://cover.png","text":"Welcome to Hexo! This is your very first post. Check documentation for more info. If you get any problems when using Hexo, you can find the ...","link":"","photos":[],"count_time":{"symbolsCount":440,"symbolsTime":"1 mins."},"categories":[{"name":"Cate","slug":"Cate","count":1,"path":"api/categories/Cate.json"}],"tags":[{"name":"Tag","slug":"Tag","count":1,"path":"api/tags/Tag.json"}],"author":{"name":"桌沿","slug":"blog-author","avatar":"https://imgs.zhubai.love/c6dfb4dd470244c5bb0835469b9d9781.png","link":"/","description":"这是一段简短的描述","socials":{"github":"https://github.com/TriDiamond","twitter":"","stackoverflow":"","wechat":"","qq":"","weibo":"","zhihu":"","csdn":"","juejin":"","customs":{"sspai":{"icon":"/svg/sspai.svg","link":"https://sspai.com/u/379wzx2e/posts"},"newsletter":{"icon":"/svg/newsletter.svg","link":"https://deskside.zhubai.love"}}}},"feature":true}],"categories":1,"tags":1,"word_count":"1.3k","post_count":3}