{"name":"好物推荐","slug":"好物推荐","count":1,"postlist":[{"title":"最高性价比的桌面照明设备奖：小米屏幕挂灯","uid":"05a12cf5d166dbc30bf66060e5fea1a2","slug":"xiaomi-display-light","date":"2022-03-18T16:00:00.000Z","updated":"2022-06-29T13:26:20.003Z","comments":true,"path":"api/articles/xiaomi-display-light.json","keywords":null,"cover":"https://s2.loli.net/2022/06/29/hjMlL6WCyV2bqr5.png","text":"本周我新购入了一个设备：小米屏幕挂灯。 混迹少数派网站的朋友们应该都了解，屡被提及的桌面必备设备「屏幕挂灯」。大部分少数派作者及员工购入的是明基的屏幕挂灯，我综合了解后发现其只有一个缺点——贵。 所幸，小米去年也推出了一款屏幕挂灯，也广受好评，价格几乎只有明基的 1 &#x2F;...","link":"","photos":[],"count_time":{"symbolsCount":385,"symbolsTime":"1 mins."},"categories":[{"name":"好物推荐","slug":"好物推荐","count":1,"path":"api/categories/好物推荐.json"}],"tags":[{"name":"工作","slug":"工作","count":2,"path":"api/tags/工作.json"},{"name":"工具","slug":"工具","count":6,"path":"api/tags/工具.json"}],"author":{"name":"桌沿","slug":"blog-author","avatar":"/img/me.png","link":"/","description":"桌沿奇思 Newsletter 主理人，少数派签约作者。欢迎订阅我的 Newsletter 哦🤭","socials":{"github":"","twitter":"","stackoverflow":"","wechat":"","qq":"","weibo":"","zhihu":"","csdn":"","juejin":"","customs":{"sspai":{"icon":"/svg/sspai.svg","link":"https://sspai.com/u/379wzx2e/posts"},"jike":{"icon":"/svg/jike.svg","link":"https://okjk.co/IktPrE"},"youtube":{"icon":"/svg/youtube.svg","link":"https://www.youtube.com/channel/UCDHwHAiT-jJ4AACLHir70Fg"},"twitter":{"icon":"/svg/twitter.svg","link":"https://twitter.com/desksidezhuoyan"},"ins":{"icon":"/svg/instagram.svg","link":"https://www.instagram.com/deskside.zhuoyan/"},"mailto":{"icon":"/svg/mailto.svg","link":"mailto:deskside.zhuoyan@outlook.com"}}}},"feature":false}]}